udemy_userAPI/__init__.py
udemy_userAPI/__version__.py
udemy_userAPI/api.py
udemy_userAPI/authenticate.py
udemy_userAPI/bultins.py
udemy_userAPI/exeptions.py
udemy_userAPI/sections.py
udemy_userAPI/udemy.py
udemy_userAPI/.cache/.udemy_userAPI
udemy_userAPI/mpd_analyzer/__init__.py
udemy_userAPI/mpd_analyzer/bin.wvd
udemy_userAPI/mpd_analyzer/mpd_parser.py
udemy_userapi-0.3.12.dist-info/licenses/LICENSE
udemy_userapi-0.3.12.dist-info/METADATA
udemy_userapi-0.3.12.dist-info/WHEEL
udemy_userapi-0.3.12.dist-info/top_level.txt
udemy_userapi-0.3.12.dist-info/RECORD
