Metadata-Version: 2.4
Name: udemy_userAPI
Version: 0.3.12
Summary: Obtenha detalhes de cursos que o usuário esteja inscrito da plataforma Udemy,usando o EndPoint de usuário o mesmo que o navegador utiliza para acessar e redenrizar os cursos.
Author: PauloCesar-dev404
Author-email: paulocesar0073dev404@gmail.com
License: MIT
Project-URL: GitHub, https://github.com/PauloCesar-dev404/udemy-userAPI
Project-URL: Bugs/Melhorias, https://github.com/PauloCesar-dev404/udemy-userAPI/issues
Project-URL: Documentação, https://github.com/PauloCesar-dev404/udemy-userAPI/wiki
Keywords: udemy,udemy python,pyudemy,udemy_userAPI,udemy api
Platform: any
License-File: LICENSE
Requires-Dist: requests
Requires-Dist: cloudscraper
Requires-Dist: pywidevine
Dynamic: author
Dynamic: author-email
Dynamic: description
Dynamic: description-content-type
Dynamic: keywords
Dynamic: license
Dynamic: license-file
Dynamic: platform
Dynamic: project-url
Dynamic: requires-dist
Dynamic: summary
